README.md
setup.py
docode_managebd/__init__.py
docode_managebd/procesos_bd.py
docode_managebd.egg-info/PKG-INFO
docode_managebd.egg-info/SOURCES.txt
docode_managebd.egg-info/dependency_links.txt
docode_managebd.egg-info/top_level.txt