Metadata-Version: 2.1
Name: docode-managebd
Version: 0.0.6
Summary: libreria para el manejo de base de datos
Home-page: https://github.com/DoCodeSoft/docode-managebd
Author: DoCode
Author-email: mario@docode.com.mx : elias@docode.com.mx
License: UNKNOWN
Platform: UNKNOWN
Classifier: Programming Language :: Python :: 3
Classifier: License :: OSI Approved :: MIT License
Classifier: Operating System :: OS Independent
Classifier: Framework :: Django
Classifier: Programming Language :: Python :: 3
Requires-Python: >=3.6
